odoo/addons/product_supplierinfo_for_customer_group/README.rst
odoo/addons/product_supplierinfo_for_customer_group/__init__.py
odoo/addons/product_supplierinfo_for_customer_group/__manifest__.py
odoo/addons/product_supplierinfo_for_customer_group/i18n/es.po
odoo/addons/product_supplierinfo_for_customer_group/i18n/it.po
odoo/addons/product_supplierinfo_for_customer_group/i18n/product_supplierinfo_for_customer_group.pot
odoo/addons/product_supplierinfo_for_customer_group/models/__init__.py
odoo/addons/product_supplierinfo_for_customer_group/models/product_customerinfo.py
odoo/addons/product_supplierinfo_for_customer_group/readme/CONFIGURE.rst
odoo/addons/product_supplierinfo_for_customer_group/readme/CONTRIBUTORS.rst
odoo/addons/product_supplierinfo_for_customer_group/readme/DESCRIPTION.rst
odoo/addons/product_supplierinfo_for_customer_group/readme/ROADMAP.rst
odoo/addons/product_supplierinfo_for_customer_group/readme/USAGE.rst
odoo/addons/product_supplierinfo_for_customer_group/static/description/icon.png
odoo/addons/product_supplierinfo_for_customer_group/static/description/index.html
odoo/addons/product_supplierinfo_for_customer_group/tests/__init__.py
odoo/addons/product_supplierinfo_for_customer_group/tests/test_product_supplierinfo_for_customer.py
odoo14_addon_product_supplierinfo_for_customer_group-14.0.1.0.1.dev7.dist-info/METADATA
odoo14_addon_product_supplierinfo_for_customer_group-14.0.1.0.1.dev7.dist-info/WHEEL
odoo14_addon_product_supplierinfo_for_customer_group-14.0.1.0.1.dev7.dist-info/top_level.txt
odoo14_addon_product_supplierinfo_for_customer_group-14.0.1.0.1.dev7.dist-info/RECORD
